<?xml version="1.0" encoding="UTF-8"?>
<Styles>
    <Style Name="Title" ID="1662B010-0245-4ECA-B12E-E978CDA3EC69" Type="Para+Char" FontChange="Size">
        <Format><![CDATA[{\rtf1\ansi\ansicpg1252\cocoartf1561\cocoasubrtf400
{\fonttbl\f0\fnil\fcharset0 Georgia;}
{\colortbl;\red255\green255\blue255;}
{\*\expandedcolortbl;;}
\pard\tx560\tx1120\tx1680\tx2240\tx2800\tx3360\tx3920\tx4480\tx5040\tx5600\tx6160\tx6720\sl312\slmult1\sb220\pardirnatural\partightenfactor0

\f0\fs56 \cf0 <$ScrKeepWithNext>Attributes}]]></Format>
    </Style>
    <Style Name="Heading 1" ID="D36C850D-3519-4BA1-AA06-CB2CF0E109CC" Type="Para+Char" FontChange="Size" Shortcut="4">
        <Format><![CDATA[{\rtf1\ansi\ansicpg1252\cocoartf1561\cocoasubrtf400
{\fonttbl\f0\fswiss\fcharset0 Helvetica;\f1\fnil\fcharset0 Georgia;}
{\colortbl;\red255\green255\blue255;}
{\*\expandedcolortbl;;}
\pard\tx560\tx1120\tx1680\tx2240\tx2800\tx3360\tx3920\tx4480\tx5040\tx5600\tx6160\tx6720\sl312\slmult1\sb220\pardirnatural\partightenfactor0

\f0\fs24 \cf0 <$ScrKeepWithNext><$Scr_H::1>
\f1\b\fs36 Attributes
\f0\b0\fs24 <!$Scr_H::1>}]]></Format>
    </Style>
    <Style Name="Heading 2" ID="FF5C301E-F453-4D9E-8216-76E7D2ECE947" Type="Para+Char" FontChange="Size" Shortcut="5">
        <Format><![CDATA[{\rtf1\ansi\ansicpg1252\cocoartf1561\cocoasubrtf400
{\fonttbl\f0\fswiss\fcharset0 Helvetica;\f1\fnil\fcharset0 Georgia;}
{\colortbl;\red255\green255\blue255;}
{\*\expandedcolortbl;;}
\pard\tx560\tx1120\tx1680\tx2240\tx2800\tx3360\tx3920\tx4480\tx5040\tx5600\tx6160\tx6720\sl312\slmult1\sb220\pardirnatural\partightenfactor0

\f0\fs24 \cf0 <$ScrKeepWithNext><$Scr_H::2>
\f1\b\fs22 Attributes
\f0\b0\fs24 <!$Scr_H::2>}]]></Format>
    </Style>
    <Style Name="Centered Text" ID="85EFF062-31CB-4F93-B546-468622932CBC" Type="Para" Shortcut="1">
        <Format><![CDATA[{\rtf1\ansi\ansicpg1252\cocoartf1561\cocoasubrtf400
{\fonttbl\f0\fnil\fcharset0 Georgia;}
{\colortbl;\red255\green255\blue255;}
{\*\expandedcolortbl;;}
\pard\tx360\tx720\tx1080\tx1440\tx1800\tx2160\tx2880\tx3600\tx4320\sl312\slmult1\pardirnatural\qc\partightenfactor0

\f0\fs22 \cf0 Attributes}]]></Format>
    </Style>
    <Style Name="Block Quote" ID="14C18AE3-8669-4E6D-878B-5F2B3316B255" Type="Para" FontChange="Size" Shortcut="2">
        <Format><![CDATA[{\rtf1\ansi\ansicpg1252\cocoartf1561\cocoasubrtf400
{\fonttbl\f0\fnil\fcharset0 Georgia;}
{\colortbl;\red255\green255\blue255;}
{\*\expandedcolortbl;;}
\pard\tx720\tx1080\tx1440\li720\sl312\slmult1\sb240\sa240\pardirnatural\partightenfactor0

\f0\fs24 \cf0 Attributes}]]></Format>
    </Style>
    <Style Name="Attribution" ID="7D2E1324-760E-4E67-A1B8-9EC9482A8E09" Type="Para" FontChange="Size" Shortcut="">
        <Format><![CDATA[{\rtf1\ansi\ansicpg1252\cocoartf1561\cocoasubrtf400
{\fonttbl\f0\fnil\fcharset0 Georgia;}
{\colortbl;\red255\green255\blue255;}
{\*\expandedcolortbl;;}
\pard\tx720\tx1080\tx1440\li720\sl312\slmult1\sa240\pardirnatural\partightenfactor0

\f0\fs24 \cf0 Attributes}]]></Format>
    </Style>
    <Style Name="Code Block" ID="7038E0AC-AB73-45C6-A40E-7B8041C71706" Type="Para+Char" FontChange="Face+Size" Next="7038E0AC-AB73-45C6-A40E-7B8041C71706">
        <Format><![CDATA[{\rtf1\ansi\ansicpg1252\cocoartf1561\cocoasubrtf400
{\fonttbl\f0\fnil\fcharset0 Menlo-Regular;}
{\colortbl;\red255\green255\blue255;}
{\*\expandedcolortbl;;}
\pard\tx720\tx1080\tx1440\tx1800\tx2160\li720\pardirnatural\partightenfactor0

\f0\fs22 \cf0 Attributes}]]></Format>
    </Style>
    <Style Name="Code Span" ID="CDF266DC-D380-4C95-AF72-C9642167BCBF" Type="Char" FontChange="Face+Size">
        <Format><![CDATA[{\rtf1\ansi\ansicpg1252\cocoartf1561\cocoasubrtf400
{\fonttbl\f0\fnil\fcharset0 Menlo-Regular;}
{\colortbl;\red255\green255\blue255;}
{\*\expandedcolortbl;;}
\pard\tx720\tx1080\tx1440\tx1800\tx2160\li720\pardirnatural\partightenfactor0

\f0\fs22 \cf0 Attributes}]]></Format>
    </Style>
    <Style Name="Caption" ID="90E9CFF0-F2DC-48CF-BA60-6129F6F918CA" Type="Para" FontChange="Size" Shortcut="3">
        <Format><![CDATA[{\rtf1\ansi\ansicpg1252\cocoartf1561\cocoasubrtf400
{\fonttbl\f0\fnil\fcharset0 Georgia;}
{\colortbl;\red255\green255\blue255;}
{\*\expandedcolortbl;;}
\pard\tx560\tx1120\tx1680\tx2240\tx2800\tx3360\tx3920\tx4480\tx5040\tx5600\tx6160\tx6720\sl312\slmult1\sa140\pardirnatural\qc\partightenfactor0

\f0\fs22 \cf0 Attributes}]]></Format>
    </Style>
    <Style Name="Emphasis" ID="334CD680-590A-43A9-8D3B-1C16A029914F" Type="Char">
        <Format><![CDATA[{\rtf1\ansi\ansicpg1252\cocoartf1561\cocoasubrtf400
{\fonttbl\f0\fnil\fcharset0 Georgia;}
{\colortbl;\red255\green255\blue255;}
{\*\expandedcolortbl;;}
\pard\tx360\tx720\tx1080\tx1440\tx1800\tx2160\tx2880\tx3600\tx4320\fi360\sl312\slmult1\pardirnatural\partightenfactor0

\f0\i\fs22 \cf0 Attributes}]]></Format>
    </Style>
</Styles>